mask_prometheus/__init__.py
mask_prometheus-1.0.0a1.dist-info/LICENSE
mask_prometheus-1.0.0a1.dist-info/METADATA
mask_prometheus-1.0.0a1.dist-info/WHEEL
mask_prometheus-1.0.0a1.dist-info/top_level.txt
mask_prometheus-1.0.0a1.dist-info/RECORD
