Metadata-Version: 2.1
Name: mask-prometheus
Version: 1.0.0a1
Summary: Prometheus extension for Mask.
Home-page: https://github.com/Eastwu5788/Mask-Prometheus
Author: Wu Dong
Author-email: wudong@eastwu.cn
License: MIT
Project-URL: Document, https://github.com/Eastwu5788/Mask-Prometheus
Project-URL: Source Code, https://github.com/Eastwu5788/Mask-Prometheus
Project-URL: Issue, https://github.com/Eastwu5788/Mask-Prometheus/issues
Platform: UNKNOWN
Requires-Python: >= 3.6
Requires-Dist: Mask (>=1.0.0a1)
Requires-Dist: Prometheus-client (>=0.11.0)
